{
    "name": "MrHustle",
    "class": "tank",
    "leader": true,
    "whistle": false,
    "loot_threshold": 9,
    "inventory": {
        "1": {
            "name": "Rare ice II",
            "magic_level": null,
            "quality_level": null,
            "damage": "13 to 15",
            "mana_cost": "13",
            "score": 0,
            "action": "sell"
        },
        "2": {
            "name": "Mythical focused heal II",
            "magic_level": null,
            "quality_level": null,
            "heals": "11 to 13",
            "mana_cost": "13",
            "Experience Gained": "+2",
            "Life Steal": "+2",
            "Critical Flux": "+1",
            "Wind Mastery": "+2",
            "score": 4,
            "action": "shrine"
        },
        "3": {
            "name": "Mystical mithril dagger",
            "magic_level": null,
            "quality_level": null,
            "level_req": "25",
            "damage": "87 to 152",
            "Enhanced Effect": "+30",
            "score": 12,
            "action": "fight_with"
        },
        "4": {
            "name": "Arcane elvan padded robe",
            "magic_level": null,
            "quality_level": null,
            "level_req": "25",
            "physical_defense": "0 to 61",
            "magical_defense": "38 to 96",
            "Enhanced Effect": "+109",
            "Life": "+1 to 10",
            "Mana": "+1 to 1",
            "Mana Consumption": "-1",
            "Glancing Blow": "+1",
            "Fire Mastery": "+2",
            "score": 27,
            "action": "fight_with"
        },
        "5": {
            "name": "Rare alloy dagger",
            "magic_level": null,
            "quality_level": null,
            "level_req": "15",
            "damage": "65 to 115",
            "Enhanced Effect": "+31",
            "score": 12,
            "action": "fight_with"
        },
        "6": {
            "name": "Magical brocade robe",
            "magic_level": null,
            "quality_level": null,
            "level_req": "10",
            "physical_defense": "0 to 12",
            "magical_defense": "16 to 48",
            "Enhanced Effect": "+40",
            "score": 14,
            "action": "fight_with"
        },
        "7": {
            "name": "Mystical steel dagger",
            "magic_level": null,
            "quality_level": null,
            "level_req": "10",
            "damage": "42 to 73",
            "Life": "+1 to 10",
            "score": 0,
            "action": "sell"
        },
        "8": {
            "name": "Arcane cotton robe",
            "magic_level": null,
            "quality_level": null,
            "physical_defense": "0 to 3",
            "magical_defense": "4 to 13",
            "Experience Gained": "+1",
            "Mana": "+1 to 2",
            "Life Steal": "+1",
            "score": 1,
            "action": "sell"
        }
    },
    "equipment": {
        "weapon": {
            "type": "iconDagger",
            "name": "Rare adamantium dagger",
            "magic_level": null,
            "quality_level": null,
            "level_req": "35",
            "damage": "143 to 251",
            "enhanced effect": "72",
            "ice mastery": "14",
            "score": 20,
            "action": "fight_with"
        },
        "armor": {
            "type": "iconPaddedRobe",
            "name": "Magical wyvernskin padded robe",
            "magic_level": null,
            "quality_level": null,
            "level_req": "40",
            "physical_defense": "0 to 79",
            "magical_defense": "49 to 124",
            "enhanced effect": "97",
            "score": 20,
            "action": "fight_with"
        },
        "charm": {
            "type": "iconEarthCharm",
            "name": "Mystical earth IV",
            "magic_level": null,
            "quality_level": null,
            "level_req": "5",
            "damage": "19 to 33",
            "enhanced effect": "4",
            "score": 4,
            "action": "fight_with"
        },
        "acc._charm": {
            "type": "iconFireCharm",
            "name": "fire XIV",
            "magic_level": null,
            "quality_level": null,
            "level_req": "55",
            "damage": "48 to 128",
            "score": 0,
            "action": "fight_with"
        }
    }
}